trattoria/__init__.py
trattoria/core.py
trattoria/postselection.py
trattoria-0.3.7.dist-info/METADATA
trattoria-0.3.7.dist-info/WHEEL
trattoria-0.3.7.dist-info/RECORD
