Metadata-Version: 2.1
Name: trattoria
Version: 0.3.7
Summary: The fastest streaming algorithms for your TTTR data
Home-page: https://github.com/GCBallesteros/trattoria
License: MIT
Author: Guillem Ballesteros
Author-email: dev+pypi@maxwellrules.com
Requires-Python: >=3.8,<3.12
Classifier: License :: OSI Approved :: MIT License
Classifier: Programming Language :: Python :: 3
Classifier: Programming Language :: Python :: 3.8
Classifier: Programming Language :: Python :: 3.9
Classifier: Programming Language :: Python :: 3.10
Classifier: Programming Language :: Python :: 3.11
Requires-Dist: numpy (>=1.20)
Requires-Dist: scipy (>=1.8)
Requires-Dist: trattoria-core (==0.4.6)
Project-URL: Repository, https://github.com/GCBallesteros/trattoria
